figures/fig.comparing_encodings_size_speed.png
figures/fig.comparing_engines.png
figures/fig.comparing_engines_serializers_encodings.png
figures/fig.comparing_serializers_size_speed.png
hashstash/__init__.py
hashstash/config.py
hashstash/constants.py
hashstash/hashstash.py
hashstash/engines/__init__.py
hashstash/engines/base.py
hashstash/engines/dataframe.py
hashstash/engines/diskcache.py
hashstash/engines/jsonl copy.py
hashstash/engines/jsonl.py
hashstash/engines/lmdb.py
hashstash/engines/memory.py
hashstash/engines/mongo.py
hashstash/engines/pairtree.py
hashstash/engines/redis.py
hashstash/engines/shelve.py
hashstash/engines/sqlite.py
hashstash/profilers/__init__.py
hashstash/profilers/engine_profiler.py
hashstash/profilers/profiler.py
hashstash/serializers/__init__.py
hashstash/serializers/custom.py
hashstash/serializers/jsons.py
hashstash/serializers/serializer.py
hashstash/utils/__init__.py
hashstash/utils/addrs.py
hashstash/utils/dataframes.py
hashstash/utils/encodings.py
hashstash/utils/logs.py
hashstash/utils/misc.py
hashstash/utils/pmap.py
hashstash/utils/wrappers.py
hashstash-0.2.13.dist-info/licenses/LICENSE
tests/test_addrs.py
tests/test_dataframes.py
tests/test_encoder.py
tests/test_engines.py
tests/test_pmap.py
tests/test_profilers.py
tests/test_serialize.py
tests/test_wrappers.py
hashstash-0.2.13.dist-info/METADATA
hashstash-0.2.13.dist-info/WHEEL
hashstash-0.2.13.dist-info/entry_points.txt
hashstash-0.2.13.dist-info/top_level.txt
hashstash-0.2.13.dist-info/RECORD
