Metadata-Version: 2.4
Name: hashstash
Version: 0.2.13
Summary: A simple file-based caching system using hash-based file names
Author-email: Dr Ryan Heuser <ryan.heuser@gmail.com>
Project-URL: Homepage, https://github.com/quadrismegistus/hashstash
Project-URL: Bug Tracker, https://github.com/quadrismegistus/hashstash/issues
Classifier: Programming Language :: Python :: 3
Classifier: License :: OSI Approved :: MIT License
Classifier: Operating System :: OS Independent
Requires-Python: >=3.7
License-File: LICENSE
Provides-Extra: jsonpickle
Requires-Dist: jsonpickle; extra == "jsonpickle"
Requires-Dist: numpy; extra == "jsonpickle"
Requires-Dist: pandas; extra == "jsonpickle"
Provides-Extra: dataframe
Requires-Dist: pandas; extra == "dataframe"
Requires-Dist: numpy; extra == "dataframe"
Requires-Dist: pyarrow; extra == "dataframe"
Requires-Dist: fastparquet; extra == "dataframe"
Provides-Extra: sqlite
Requires-Dist: sqlitedict; extra == "sqlite"
Provides-Extra: redis
Requires-Dist: redis; extra == "redis"
Requires-Dist: redis_dict; extra == "redis"
Provides-Extra: mongo
Requires-Dist: pymongo; extra == "mongo"
Provides-Extra: lmdb
Requires-Dist: lmdb; extra == "lmdb"
Provides-Extra: diskcache
Requires-Dist: diskcache; extra == "diskcache"
Provides-Extra: memory
Requires-Dist: ultradict; extra == "memory"
Provides-Extra: filebased
Requires-Dist: pandas; extra == "filebased"
Requires-Dist: polars; extra == "filebased"
Requires-Dist: numpy; extra == "filebased"
Requires-Dist: pyarrow; extra == "filebased"
Requires-Dist: fastparquet; extra == "filebased"
Requires-Dist: sqlitedict; extra == "filebased"
Requires-Dist: diskcache; extra == "filebased"
Requires-Dist: lmdb; extra == "filebased"
Requires-Dist: ultradict; extra == "filebased"
Provides-Extra: servers
Requires-Dist: redis; extra == "servers"
Requires-Dist: redis_dict; extra == "servers"
Requires-Dist: pymongo; extra == "servers"
Provides-Extra: engines
Requires-Dist: pandas; extra == "engines"
Requires-Dist: polars; extra == "engines"
Requires-Dist: numpy; extra == "engines"
Requires-Dist: pyarrow; extra == "engines"
Requires-Dist: fastparquet; extra == "engines"
Requires-Dist: lmdb; extra == "engines"
Requires-Dist: sqlitedict; extra == "engines"
Requires-Dist: diskcache; extra == "engines"
Requires-Dist: redis; extra == "engines"
Requires-Dist: redis_dict; extra == "engines"
Requires-Dist: mongo; extra == "engines"
Requires-Dist: ultradict; extra == "engines"
Provides-Extra: dev
Requires-Dist: pandas; extra == "dev"
Requires-Dist: polars; extra == "dev"
Requires-Dist: numpy; extra == "dev"
Requires-Dist: pyarrow; extra == "dev"
Requires-Dist: fastparquet; extra == "dev"
Requires-Dist: lmdb; extra == "dev"
Requires-Dist: sqlitedict; extra == "dev"
Requires-Dist: diskcache; extra == "dev"
Requires-Dist: redis; extra == "dev"
Requires-Dist: redis_dict; extra == "dev"
Requires-Dist: mongo; extra == "dev"
Requires-Dist: ultradict; extra == "dev"
Requires-Dist: jsonpickle; extra == "dev"
Requires-Dist: orjson; extra == "dev"
Requires-Dist: tqdm; extra == "dev"
Requires-Dist: plotnine; extra == "dev"
Requires-Dist: scikit-misc; extra == "dev"
Requires-Dist: pytest; extra == "dev"
Requires-Dist: pytest-cov; extra == "dev"
Requires-Dist: setuptools-scm; extra == "dev"
Requires-Dist: ipython; extra == "dev"
Provides-Extra: all
Requires-Dist: pandas; extra == "all"
Requires-Dist: polars; extra == "all"
Requires-Dist: numpy; extra == "all"
Requires-Dist: pyarrow; extra == "all"
Requires-Dist: fastparquet; extra == "all"
Requires-Dist: lmdb; extra == "all"
Requires-Dist: sqlitedict; extra == "all"
Requires-Dist: diskcache; extra == "all"
Requires-Dist: redis; extra == "all"
Requires-Dist: redis_dict; extra == "all"
Requires-Dist: mongo; extra == "all"
Requires-Dist: ultradict; extra == "all"
Requires-Dist: jsonpickle; extra == "all"
Requires-Dist: orjson; extra == "all"
Requires-Dist: lz4; extra == "all"
Requires-Dist: blosc; extra == "all"
Requires-Dist: tqdm; extra == "all"
Requires-Dist: plotnine; extra == "all"
Requires-Dist: scikit-misc; extra == "all"
Provides-Extra: rec
Requires-Dist: pandas; extra == "rec"
Requires-Dist: pyarrow; extra == "rec"
Requires-Dist: lmdb; extra == "rec"
Requires-Dist: lz4; extra == "rec"
Requires-Dist: ultradict; extra == "rec"
Dynamic: license-file
